{
    "dev": {
        "awscloudformation": {
            "AuthRoleName": "amplify-vorderio-dev-123626-authRole",
            "UnauthRoleArn": "arn:aws:iam::828009597444:role/amplify-vorderio-dev-123626-unauthRole",
            "AuthRoleArn": "arn:aws:iam::828009597444:role/amplify-vorderio-dev-123626-authRole",
            "Region": "us-east-2",
            "DeploymentBucketName": "amplify-vorderio-dev-123626-deployment",
            "UnauthRoleName": "amplify-vorderio-dev-123626-unauthRole",
            "StackName": "amplify-vorderio-dev-123626",
            "StackId": "arn:aws:cloudformation:us-east-2:828009597444:stack/amplify-vorderio-dev-123626/1f556260-bbbb-11eb-ba61-0aadfdbcbf52",
            "AmplifyAppId": "d3t0m49n15qnd3"
        },
        "categories": {
            "hosting": {
                "amplifyhosting": {
                    "appId": "d3t0m49n15qnd3",
                    "type": "manual"
                }
            }
        }
    }
}